squeemtools/__init__.py
squeemtools/graphing/Graphing.py
squeemtools/graphing/__init__.py
squeemtools/math/FCM.py
squeemtools/math/Helpers.py
squeemtools/math/ID3.py
squeemtools/math/KMeans.py
squeemtools/math/LinearRegression.py
squeemtools/math/PLA.py
squeemtools/math/__init__.py
squeemtools/other/ClusterImage.py
squeemtools/other/Dictionaries.py
squeemtools/other/EmailDone.py
squeemtools/other/LoadGLMData.py
squeemtools/other/__init__.py
squeemtools-1.1.2.dist-info/LICENSE.txt
squeemtools-1.1.2.dist-info/METADATA
squeemtools-1.1.2.dist-info/WHEEL
squeemtools-1.1.2.dist-info/top_level.txt
squeemtools-1.1.2.dist-info/RECORD
