Metadata-Version: 2.1
Name: squeemtools
Version: 1.1.2
Summary: Packages of misceallaneous use. Combination of all things created/used for projects.
Home-page: https://github.com/Squeemos/SqueemTools
Author: Ben van Oostendorp
Author-email: ben.vano@digipen.edu
License: MIT
Download-URL: https://github.com/Squeemos/SqueemTools/archive/SqueemTools_1.1.2.tar.gz
Keywords: GRAPHING,FUZZY C MEANS,GLM,ID3
Platform: UNKNOWN
Classifier: Development Status :: 3 - Alpha
Classifier: Intended Audience :: Developers
Classifier: Topic :: Software Development :: Build Tools
Classifier: License :: OSI Approved :: MIT License
Classifier: Programming Language :: Python :: 3.8
Requires-Dist: matplotlib
Requires-Dist: numpy
Requires-Dist: pandas
Requires-Dist: numdifftools
Requires-Dist: scipy
Requires-Dist: xarray
Requires-Dist: sklearn
